quart_disnake/__init__.py
quart_disnake/_http.py
quart_disnake/client.py
quart_disnake/configs.py
quart_disnake/exceptions.py
quart_disnake/utils.py
quart_disnake/models/__init__.py
quart_disnake/models/base.py
quart_disnake/models/connections.py
quart_disnake/models/guild.py
quart_disnake/models/integration.py
quart_disnake/models/user.py
tests/__init__.py
tests/test_app.py
Quart_Disnake_Oauth2-2.1.7.dist-info/METADATA
Quart_Disnake_Oauth2-2.1.7.dist-info/WHEEL
Quart_Disnake_Oauth2-2.1.7.dist-info/top_level.txt
Quart_Disnake_Oauth2-2.1.7.dist-info/RECORD
