Metadata-Version: 2.1
Name: Quart-Disnake-Oauth2
Version: 2.1.7
Summary: Discord OAuth2 extension for Quart.
Home-page: 
Author: Sscefalix
Author-email: dimabykov189@gmail.com
License: MIT
Platform: any
Classifier: Environment :: Web Environment
Classifier: Intended Audience :: Developers
Classifier: License :: OSI Approved :: MIT License
Classifier: Operating System :: OS Independent
Classifier: Programming Language :: Python
Classifier: Topic :: Internet :: WWW/HTTP :: Dynamic Content
Classifier: Topic :: Software Development :: Libraries :: Python Modules
Requires-Dist: Quart
Requires-Dist: pyjwt
Requires-Dist: oauthlib
Requires-Dist: Async-OAuthlib
Requires-Dist: cachetools
Requires-Dist: disnake
